.gitignore
AUTHOR
CHANGELOG.rst
LICENSE
MANIFEST.in
README.rst
TODO.rst
logo.png
pynfact.toml
setup.cfg
setup.py
doc/Makefile
doc/conf.py
doc/index.rst
doc/meta/CHANGELOG.rst
doc/meta/LICENSE.rst
doc/meta/README.rst
doc/meta/TODO.rst
doc/src/modules.rst
doc/src/pynfact.rst
doc/userdoc/configuration.rst
doc/userdoc/dependencies.rst
doc/userdoc/document-syntax.rst
doc/userdoc/error-codes.rst
doc/userdoc/index.rst
doc/userdoc/install-and-upgrade.rst
doc/userdoc/intro.rst
doc/userdoc/logo.png
doc/userdoc/quickstart.rst
doc/userdoc/site-content.rst
doc/userdoc/versioning.rst
pynfact/__init__.py
pynfact/__main__.py
pynfact/builder.py
pynfact/cli.py
pynfact/dataman.py
pynfact/fileman.py
pynfact/main.py
pynfact/meta.py
pynfact/parser.py
pynfact/server.py
pynfact/struri.py
pynfact/yamler.py
pynfact.egg-info/PKG-INFO
pynfact.egg-info/SOURCES.txt
pynfact.egg-info/dependency_links.txt
pynfact.egg-info/entry_points.txt
pynfact.egg-info/requires.txt
pynfact.egg-info/top_level.txt
pynfact/data/initnew/config.yml
pynfact/data/initnew/pages/about-me.md
pynfact/data/initnew/posts/TEMPLATE.md.no
pynfact/data/initnew/posts/TEMPLATE.rst.no
pynfact/data/initnew/posts/first_entry.md
pynfact/data/initnew/static/css/pygments.css
pynfact/data/initnew/static/css/reg_paragraphs.css
pynfact/data/initnew/static/css/reg_quotes.css
pynfact/data/initnew/static/css/reset.css
pynfact/data/initnew/static/css/style_dark.css
pynfact/data/initnew/static/css/style_light.css
pynfact/data/initnew/templates/archive.html.j2
pynfact/data/initnew/templates/base.html.j2
pynfact/data/initnew/templates/cat.html.j2
pynfact/data/initnew/templates/catcloud.html.j2
pynfact/data/initnew/templates/catlist.html.j2
pynfact/data/initnew/templates/entries.html.j2
pynfact/data/initnew/templates/entry.html.j2
pynfact/data/initnew/templates/page.html.j2
pynfact/data/initnew/templates/tag.html.j2
pynfact/data/initnew/templates/tagcloud.html.j2
pynfact/data/locale/default.pot
pynfact/data/locale/ca_ES/LC_MESSAGES/default.mo
pynfact/data/locale/ca_ES/LC_MESSAGES/default.po
pynfact/data/locale/en_AU/LC_MESSAGES/default.mo
pynfact/data/locale/en_AU/LC_MESSAGES/default.po
