Metadata-Version: 2.4
Name: pynfact
Version: 1.3.5
Summary: Blog-oriented static website generator using Markdown or reStructuredText.
Home-page: https://github.com/jacorbal/pynfact/wiki
Download-URL: https://github.com/jacorbal/pynfact
Author: J. A. Corbal
Author-email: jacorbal@gmail.com
License-Expression: MIT
Project-URL: Documentation, https://github.com/jacorbal/pynfact/wiki
Project-URL: Funding, https://jacorbal.es/pynfact
Project-URL: Source, https://github.com/jacorbal/pynfact
Project-URL: Tracker, https://github.com/jacorbal/pynfact/issues
Keywords: blog,markdown,restructuredtext,static,web,site,generator
Platform: any
Classifier: Development Status :: 5 - Production/Stable
Classifier: Environment :: Console
Classifier: Intended Audience :: Developers
Classifier: Intended Audience :: End Users/Desktop
Classifier: Operating System :: OS Independent
Classifier: Programming Language :: Python :: 3
Classifier: Programming Language :: Python :: 3.6
Classifier: Programming Language :: Python :: 3.7
Classifier: Programming Language :: Python :: 3.8
Classifier: Topic :: Internet
Classifier: Topic :: Internet :: WWW/HTTP
Classifier: Topic :: Internet :: WWW/HTTP :: Site Management
Classifier: Topic :: Software Development :: Code Generators
Classifier: Topic :: Text Processing :: Markup :: HTML
Classifier: Topic :: Utilities
Requires-Python: >=3.8
License-File: LICENSE
Requires-Dist: feedgen>=0.9.0
Requires-Dist: docutils>=0.15
Requires-Dist: jinja2>=2.7
Requires-Dist: markdown>=3.0.0
Requires-Dist: pygments>=2.0.2
Requires-Dist: python-dateutil>=2.0
Requires-Dist: pyyaml>=5.1
Requires-Dist: unidecode>=0.4.9
Requires-Dist: setuptools>=61.0.0
Dynamic: author
Dynamic: author-email
Dynamic: classifier
Dynamic: description
Dynamic: description-content-type
Dynamic: download-url
Dynamic: home-page
Dynamic: keywords
Dynamic: license
Dynamic: license-file
Dynamic: license-expression
Dynamic: platform
Dynamic: project-url
Dynamic: requires-dist
Dynamic: requires-python
Dynamic: summary
